[
    {
        "resourceType": "ConceptMap",
        "status": "draft",
        "name": "Ureter.Res",
        "title": "Ureter.Res",
        "experimental": true,
        "date": "2022-04-19",
        "publisher": "College of American Pathologists",
        "contact": [
            {
                "telecom": [
                    {
                        "system": "email",
                        "value": "agoel@cap.org"
                    }
                ]
            }
        ],
        "description": "mapping of SNOMED to CAP CKeys",
        "purpose": "mapping of SNOMED to CAP CKeys",
        "copyright": "College of American Pathologists 2022",
        "group": [
            {
                "source": "http://cap.org/eCC",
                "target": "http://snomed.info/sct",
                "element": [
                    {
                        "code": "22376.1",
                        "display": "",
                        "target": [
                            {
                                "code": "",
                                "display": "",
                                "equivalence": "equivalent"
                            }
                        ]
                    },
                    {
                        "code": "11814.1",
                        "display": "Specimen Site",
                        "target": [
                            {
                                "code": "",
                                "display": "",
                                "equivalence": "equivalent"
                            }
                        ]
                    },
                    {
                        "code": "14529.1",
                        "display": "Ureter structure",
                        "target": [
                            {
                                "code": "",
                                "display": "",
                                "equivalence": "equivalent"
                            }
                        ]
                    },
                    {
                        "code": "22377.1",
                        "display": "Tumor Site",
                        "target": [
                            {
                                "code": "399687005 |Anatomic location of primary malignant neoplasm (observable entity)|",
                                "display": "",
                                "equivalence": "equivalent"
                            }
                        ]
                    },
                    {
                        "code": "22378.1",
                        "display": "Ureter structure",
                        "target": [
                            {
                                "code": "",
                                "display": "",
                                "equivalence": "equivalent"
                            }
                        ]
                    },
                    {
                        "code": "18098.1",
                        "display": "SPECIMEN",
                        "target": [
                            {
                                "code": "",
                                "display": "",
                                "equivalence": "equivalent"
                            }
                        ]
                    },
                    {
                        "code": "11989.1",
                        "display": "Procedure",
                        "target": [
                            {
                                "code": "2620001000004108 |Specimen collection procedure (observable entity)|",
                                "display": "",
                                "equivalence": "equivalent"
                            }
                        ]
                    },
                    {
                        "code": "11990.1",
                        "display": "Ureterectomy",
                        "target": [
                            {
                                "code": "",
                                "display": "",
                                "equivalence": "equivalent"
                            }
                        ]
                    },
                    {
                        "code": "11992.1",
                        "display": "Other (specify)",
                        "target": [
                            {
                                "code": "",
                                "display": "",
                                "equivalence": "equivalent"
                            }
                        ]
                    },
                    {
                        "code": "11993.1",
                        "display": "Not specified",
                        "target": [
                            {
                                "code": "",
                                "display": "",
                                "equivalence": "equivalent"
                            }
                        ]
                    },
                    {
                        "code": "12000.1",
                        "display": "Specimen Laterality",
                        "target": [
                            {
                                "code": "",
                                "display": "",
                                "equivalence": "equivalent"
                            }
                        ]
                    },
                    {
                        "code": "12004.1",
                        "display": "Right",
                        "target": [
                            {
                                "code": "",
                                "display": "",
                                "equivalence": "equivalent"
                            }
                        ]
                    },
                    {
                        "code": "12007.1",
                        "display": "Left",
                        "target": [
                            {
                                "code": "",
                                "display": "",
                                "equivalence": "equivalent"
                            }
                        ]
                    },
                    {
                        "code": "12125.1",
                        "display": "Not specified",
                        "target": [
                            {
                                "code": "",
                                "display": "",
                                "equivalence": "equivalent"
                            }
                        ]
                    },
                    {
                        "code": "12126.1",
                        "display": "Tumor Size",
                        "target": [
                            {
                                "code": "",
                                "display": "",
                                "equivalence": "equivalent"
                            }
                        ]
                    },
                    {
                        "code": "12129.1",
                        "display": "Greatest dimension (cm)",
                        "target": [
                            {
                                "code": "200001000004104 |Greatest length dimension of excised primary malignant neoplasm (observable entity)|",
                                "display": "",
                                "equivalence": "equivalent"
                            }
                        ]
                    },
                    {
                        "code": "12131.1",
                        "display": "Additional Dimension (cm)",
                        "target": [
                            {
                                "code": "",
                                "display": "",
                                "equivalence": "equivalent"
                            }
                        ]
                    },
                    {
                        "code": "12130.1",
                        "display": "Additional Dimension (cm)",
                        "target": [
                            {
                                "code": "",
                                "display": "",
                                "equivalence": "equivalent"
                            }
                        ]
                    },
                    {
                        "code": "12128.1",
                        "display": "Cannot be determined (explain)",
                        "target": [
                            {
                                "code": "1156316003 |Cannot be determined (qualifier value)|",
                                "display": "",
                                "equivalence": "equivalent"
                            }
                        ]
                    },
                    {
                        "code": "18099.1",
                        "display": "TUMOR",
                        "target": [
                            {
                                "code": "",
                                "display": "",
                                "equivalence": "equivalent"
                            }
                        ]
                    },
                    {
                        "code": "27440.1",
                        "display": "Tumor Type",
                        "target": [
                            {
                                "code": "",
                                "display": "",
                                "equivalence": "equivalent"
                            }
                        ]
                    },
                    {
                        "code": "27441.1",
                        "display": "Invasive carcinoma",
                        "target": [
                            {
                                "code": "",
                                "display": "",
                                "equivalence": "equivalent"
                            }
                        ]
                    },
                    {
                        "code": "12133.1",
                        "display": "Invasive Histologic Type (Note B)",
                        "target": [
                            {
                                "code": "",
                                "display": "",
                                "equivalence": "equivalent"
                            }
                        ]
                    },
                    {
                        "code": "12134.1",
                        "display": "Urothelial (transitional cell) carcinoma",
                        "target": [
                            {
                                "code": "",
                                "display": "",
                                "equivalence": "equivalent"
                            }
                        ]
                    },
                    {
                        "code": "12135.1",
                        "display": "Urothelial (transitional cell) carcinoma with squamous differentiation",
                        "target": [
                            {
                                "code": "",
                                "display": "",
                                "equivalence": "equivalent"
                            }
                        ]
                    },
                    {
                        "code": "12143.1",
                        "display": "Urothelial (transitional cell) carcinoma with glandular differentiation",
                        "target": [
                            {
                                "code": "",
                                "display": "",
                                "equivalence": "equivalent"
                            }
                        ]
                    },
                    {
                        "code": "12173.1",
                        "display": "Urothelial (transitional cell) carcinoma with variant histology (specify type)",
                        "target": [
                            {
                                "code": "",
                                "display": "",
                                "equivalence": "equivalent"
                            }
                        ]
                    },
                    {
                        "code": "12182.1",
                        "display": "Squamous cell carcinoma, typical",
                        "target": [
                            {
                                "code": "",
                                "display": "",
                                "equivalence": "equivalent"
                            }
                        ]
                    },
                    {
                        "code": "12186.1",
                        "display": "Squamous cell carcinoma, variant histology (specify type)",
                        "target": [
                            {
                                "code": "",
                                "display": "",
                                "equivalence": "equivalent"
                            }
                        ]
                    },
                    {
                        "code": "12194.1",
                        "display": "Adenocarcinoma, typical",
                        "target": [
                            {
                                "code": "",
                                "display": "",
                                "equivalence": "equivalent"
                            }
                        ]
                    },
                    {
                        "code": "12223.1",
                        "display": "Adenocarcinoma, variant histology (specify type)",
                        "target": [
                            {
                                "code": "",
                                "display": "",
                                "equivalence": "equivalent"
                            }
                        ]
                    },
                    {
                        "code": "12232.1",
                        "display": "Small cell carcinoma",
                        "target": [
                            {
                                "code": "",
                                "display": "",
                                "equivalence": "equivalent"
                            }
                        ]
                    },
                    {
                        "code": "12235.1",
                        "display": "Undifferentiated carcinoma (specify type)",
                        "target": [
                            {
                                "code": "",
                                "display": "",
                                "equivalence": "equivalent"
                            }
                        ]
                    },
                    {
                        "code": "12237.1",
                        "display": "Mixed cell type (specify type)",
                        "target": [
                            {
                                "code": "",
                                "display": "",
                                "equivalence": "equivalent"
                            }
                        ]
                    },
                    {
                        "code": "12257.1",
                        "display": "Other (specify)",
                        "target": [
                            {
                                "code": "",
                                "display": "",
                                "equivalence": "equivalent"
                            }
                        ]
                    },
                    {
                        "code": "12258.1",
                        "display": "Carcinoma, type cannot be determined",
                        "target": [
                            {
                                "code": "",
                                "display": "",
                                "equivalence": "equivalent"
                            }
                        ]
                    },
                    {
                        "code": "27451.1",
                        "display": "Non-invasive  (papillary) urothelial carcinoma",
                        "target": [
                            {
                                "code": "",
                                "display": "",
                                "equivalence": "equivalent"
                            }
                        ]
                    },
                    {
                        "code": "27452.1",
                        "display": "Non-invasive Histologic Type (Note B)",
                        "target": [
                            {
                                "code": "",
                                "display": "",
                                "equivalence": "equivalent"
                            }
                        ]
                    },
                    {
                        "code": "27453.1",
                        "display": "Non-invasive urothelial (transitional cell) carcinoma",
                        "target": [
                            {
                                "code": "",
                                "display": "",
                                "equivalence": "equivalent"
                            }
                        ]
                    },
                    {
                        "code": "27454.1",
                        "display": "Non-invasive urothelial (transitional cell) carcinoma with squamous differentiation",
                        "target": [
                            {
                                "code": "",
                                "display": "",
                                "equivalence": "equivalent"
                            }
                        ]
                    },
                    {
                        "code": "27455.1",
                        "display": "Non-invasive urothelial (transitional cell) carcinoma with glandular differentiation",
                        "target": [
                            {
                                "code": "",
                                "display": "",
                                "equivalence": "equivalent"
                            }
                        ]
                    },
                    {
                        "code": "27456.1",
                        "display": "Non-invasive urothelial (transitional cell) carcinoma with variant histology (specify)",
                        "target": [
                            {
                                "code": "",
                                "display": "",
                                "equivalence": "equivalent"
                            }
                        ]
                    },
                    {
                        "code": "27442.1",
                        "display": "Carcinoma in situ (flat / non-papillary)",
                        "target": [
                            {
                                "code": "",
                                "display": "",
                                "equivalence": "equivalent"
                            }
                        ]
                    },
                    {
                        "code": "27443.1",
                        "display": "In Situ Histologic Type (Note B)",
                        "target": [
                            {
                                "code": "",
                                "display": "",
                                "equivalence": "equivalent"
                            }
                        ]
                    },
                    {
                        "code": "27444.1",
                        "display": "Urothelial (transitional cell) carcinoma in situ",
                        "target": [
                            {
                                "code": "",
                                "display": "",
                                "equivalence": "equivalent"
                            }
                        ]
                    },
                    {
                        "code": "27445.1",
                        "display": "Squamous cell carcinoma in situ",
                        "target": [
                            {
                                "code": "",
                                "display": "",
                                "equivalence": "equivalent"
                            }
                        ]
                    },
                    {
                        "code": "27446.1",
                        "display": "Adenocarcinoma in situ",
                        "target": [
                            {
                                "code": "",
                                "display": "",
                                "equivalence": "equivalent"
                            }
                        ]
                    },
                    {
                        "code": "27447.1",
                        "display": "Small cell carcinoma in situ",
                        "target": [
                            {
                                "code": "",
                                "display": "",
                                "equivalence": "equivalent"
                            }
                        ]
                    },
                    {
                        "code": "27448.1",
                        "display": "Mixed cell type in situ (specify)",
                        "target": [
                            {
                                "code": "",
                                "display": "",
                                "equivalence": "equivalent"
                            }
                        ]
                    },
                    {
                        "code": "27449.1",
                        "display": "Other in situ (specify)",
                        "target": [
                            {
                                "code": "",
                                "display": "",
                                "equivalence": "equivalent"
                            }
                        ]
                    },
                    {
                        "code": "27450.1",
                        "display": "Carcinoma, type cannot be determined",
                        "target": [
                            {
                                "code": "",
                                "display": "",
                                "equivalence": "equivalent"
                            }
                        ]
                    },
                    {
                        "code": "27457.1",
                        "display": "Other (specify histologic type)",
                        "target": [
                            {
                                "code": "",
                                "display": "",
                                "equivalence": "equivalent"
                            }
                        ]
                    },
                    {
                        "code": "53717.1",
                        "display": "Histologic Grade (Note C)",
                        "target": [
                            {
                                "code": "",
                                "display": "",
                                "equivalence": "equivalent"
                            }
                        ]
                    },
                    {
                        "code": "26660.1",
                        "display": "Not applicable",
                        "target": [
                            {
                                "code": "",
                                "display": "",
                                "equivalence": "equivalent"
                            }
                        ]
                    },
                    {
                        "code": "26608.1",
                        "display": "Cannot be determined",
                        "target": [
                            {
                                "code": "1156316003 |Cannot be determined (qualifier value)|",
                                "display": "",
                                "equivalence": "equivalent"
                            }
                        ]
                    },
                    {
                        "code": "41185.1",
                        "display": "For urothelial carcinoma, other variants, or divergent differentiation",
                        "target": [
                            {
                                "code": "",
                                "display": "",
                                "equivalence": "equivalent"
                            }
                        ]
                    },
                    {
                        "code": "12275.1",
                        "display": "Low-grade",
                        "target": [
                            {
                                "code": "",
                                "display": "",
                                "equivalence": "equivalent"
                            }
                        ]
                    },
                    {
                        "code": "12276.1",
                        "display": "High-grade",
                        "target": [
                            {
                                "code": "",
                                "display": "",
                                "equivalence": "equivalent"
                            }
                        ]
                    },
                    {
                        "code": "43807.1",
                        "display": "For squamous cell carcinoma or adenocarcinoma",
                        "target": [
                            {
                                "code": "",
                                "display": "",
                                "equivalence": "equivalent"
                            }
                        ]
                    },
                    {
                        "code": "12435.1",
                        "display": "GX: Cannot be assessed",
                        "target": [
                            {
                                "code": "",
                                "display": "",
                                "equivalence": "equivalent"
                            }
                        ]
                    },
                    {
                        "code": "12436.1",
                        "display": "G1: Well differentiated",
                        "target": [
                            {
                                "code": "",
                                "display": "",
                                "equivalence": "equivalent"
                            }
                        ]
                    },
                    {
                        "code": "12437.1",
                        "display": "G2: Moderately differentiated",
                        "target": [
                            {
                                "code": "",
                                "display": "",
                                "equivalence": "equivalent"
                            }
                        ]
                    },
                    {
                        "code": "12438.1",
                        "display": "G3: Poorly differentiated",
                        "target": [
                            {
                                "code": "",
                                "display": "",
                                "equivalence": "equivalent"
                            }
                        ]
                    },
                    {
                        "code": "53199.1",
                        "display": "",
                        "target": [
                            {
                                "code": "",
                                "display": "",
                                "equivalence": "equivalent"
                            }
                        ]
                    },
                    {
                        "code": "12430.1",
                        "display": "Other (specify)",
                        "target": [
                            {
                                "code": "",
                                "display": "",
                                "equivalence": "equivalent"
                            }
                        ]
                    },
                    {
                        "code": "27497.1",
                        "display": "EXTENT",
                        "target": [
                            {
                                "code": "",
                                "display": "",
                                "equivalence": "equivalent"
                            }
                        ]
                    },
                    {
                        "code": "27498.1",
                        "display": "Microscopic Tumor Extension (Note E)",
                        "target": [
                            {
                                "code": "",
                                "display": "",
                                "equivalence": "equivalent"
                            }
                        ]
                    },
                    {
                        "code": "27499.1",
                        "display": "Cannot be assessed",
                        "target": [
                            {
                                "code": "",
                                "display": "",
                                "equivalence": "equivalent"
                            }
                        ]
                    },
                    {
                        "code": "27500.1",
                        "display": "No evidence of primary tumor",
                        "target": [
                            {
                                "code": "",
                                "display": "",
                                "equivalence": "equivalent"
                            }
                        ]
                    },
                    {
                        "code": "27501.1",
                        "display": "Papillary noninvasive carcinoma",
                        "target": [
                            {
                                "code": "",
                                "display": "",
                                "equivalence": "equivalent"
                            }
                        ]
                    },
                    {
                        "code": "27502.1",
                        "display": "Carcinoma in situ",
                        "target": [
                            {
                                "code": "",
                                "display": "",
                                "equivalence": "equivalent"
                            }
                        ]
                    },
                    {
                        "code": "27503.1",
                        "display": "Tumor invades subepithelial connective tissue",
                        "target": [
                            {
                                "code": "",
                                "display": "",
                                "equivalence": "equivalent"
                            }
                        ]
                    },
                    {
                        "code": "27504.1",
                        "display": "Tumor invades the muscularis",
                        "target": [
                            {
                                "code": "",
                                "display": "",
                                "equivalence": "equivalent"
                            }
                        ]
                    },
                    {
                        "code": "27505.1",
                        "display": "Tumor invades beyond muscularis into periureteric fat",
                        "target": [
                            {
                                "code": "",
                                "display": "",
                                "equivalence": "equivalent"
                            }
                        ]
                    },
                    {
                        "code": "27506.1",
                        "display": "Tumor invades adjacent organs",
                        "target": [
                            {
                                "code": "",
                                "display": "",
                                "equivalence": "equivalent"
                            }
                        ]
                    },
                    {
                        "code": "18101.1",
                        "display": "MARGINS (Note G)",
                        "target": [
                            {
                                "code": "",
                                "display": "",
                                "equivalence": "equivalent"
                            }
                        ]
                    },
                    {
                        "code": "27459.1",
                        "display": "# If the specimen is received unoriented, precluding identification of margins as distal or proximal, it should be denoted here.",
                        "target": [
                            {
                                "code": "",
                                "display": "",
                                "equivalence": "equivalent"
                            }
                        ]
                    },
                    {
                        "code": "27463.1",
                        "display": "Margin Involvement",
                        "target": [
                            {
                                "code": "",
                                "display": "",
                                "equivalence": "equivalent"
                            }
                        ]
                    },
                    {
                        "code": "3936.100004",
                        "display": "Cannot be assessed",
                        "target": [
                            {
                                "code": "",
                                "display": "",
                                "equivalence": "equivalent"
                            }
                        ]
                    },
                    {
                        "code": "12618.1",
                        "display": "Margin(s) involved by invasive carcinoma",
                        "target": [
                            {
                                "code": "",
                                "display": "",
                                "equivalence": "equivalent"
                            }
                        ]
                    },
                    {
                        "code": "27028.1",
                        "display": "",
                        "target": [
                            {
                                "code": "",
                                "display": "",
                                "equivalence": "equivalent"
                            }
                        ]
                    },
                    {
                        "code": "27019.1",
                        "display": "Proximal mucosal margin",
                        "target": [
                            {
                                "code": "",
                                "display": "",
                                "equivalence": "equivalent"
                            }
                        ]
                    },
                    {
                        "code": "27020.1",
                        "display": "Distal mucosal margin",
                        "target": [
                            {
                                "code": "",
                                "display": "",
                                "equivalence": "equivalent"
                            }
                        ]
                    },
                    {
                        "code": "27021.1",
                        "display": "Deep soft tissue margin",
                        "target": [
                            {
                                "code": "",
                                "display": "",
                                "equivalence": "equivalent"
                            }
                        ]
                    },
                    {
                        "code": "25626.1",
                        "display": "Other margin(s) (specify)#",
                        "target": [
                            {
                                "code": "",
                                "display": "",
                                "equivalence": "equivalent"
                            }
                        ]
                    },
                    {
                        "code": "27022.1",
                        "display": "Margin(s) involved by carcinoma in situ / non-invasive high-grade urothelial carcinoma",
                        "target": [
                            {
                                "code": "",
                                "display": "",
                                "equivalence": "equivalent"
                            }
                        ]
                    },
                    {
                        "code": "27023.1",
                        "display": "",
                        "target": [
                            {
                                "code": "",
                                "display": "",
                                "equivalence": "equivalent"
                            }
                        ]
                    },
                    {
                        "code": "27024.1",
                        "display": "Proximal mucosal margin",
                        "target": [
                            {
                                "code": "",
                                "display": "",
                                "equivalence": "equivalent"
                            }
                        ]
                    },
                    {
                        "code": "27025.1",
                        "display": "Distal mucosal margin",
                        "target": [
                            {
                                "code": "",
                                "display": "",
                                "equivalence": "equivalent"
                            }
                        ]
                    },
                    {
                        "code": "27027.1",
                        "display": "Other margin(s) (specify)#",
                        "target": [
                            {
                                "code": "",
                                "display": "",
                                "equivalence": "equivalent"
                            }
                        ]
                    },
                    {
                        "code": "27029.1",
                        "display": "Margins uninvolved by invasive carcinoma / carcinoma in situ / non-invasive high-grade urothelial carcinoma",
                        "target": [
                            {
                                "code": "",
                                "display": "",
                                "equivalence": "equivalent"
                            }
                        ]
                    },
                    {
                        "code": "26986.1",
                        "display": "Distance of Carcinoma from Closest Margin",
                        "target": [
                            {
                                "code": "",
                                "display": "",
                                "equivalence": "equivalent"
                            }
                        ]
                    },
                    {
                        "code": "26988.1",
                        "display": "Specify (mm)",
                        "target": [
                            {
                                "code": "",
                                "display": "",
                                "equivalence": "equivalent"
                            }
                        ]
                    },
                    {
                        "code": "26987.1",
                        "display": "Cannot be assessed (explain)",
                        "target": [
                            {
                                "code": "",
                                "display": "",
                                "equivalence": "equivalent"
                            }
                        ]
                    },
                    {
                        "code": "26989.1",
                        "display": "Closest Margin",
                        "target": [
                            {
                                "code": "",
                                "display": "",
                                "equivalence": "equivalent"
                            }
                        ]
                    },
                    {
                        "code": "26990.1",
                        "display": "Proximal mucosal margin",
                        "target": [
                            {
                                "code": "",
                                "display": "",
                                "equivalence": "equivalent"
                            }
                        ]
                    },
                    {
                        "code": "26991.1",
                        "display": "Distal mucosal margin",
                        "target": [
                            {
                                "code": "",
                                "display": "",
                                "equivalence": "equivalent"
                            }
                        ]
                    },
                    {
                        "code": "26992.1",
                        "display": "Deep soft tissue margin",
                        "target": [
                            {
                                "code": "",
                                "display": "",
                                "equivalence": "equivalent"
                            }
                        ]
                    },
                    {
                        "code": "26993.1",
                        "display": "Other margin(s) (specify)#",
                        "target": [
                            {
                                "code": "",
                                "display": "",
                                "equivalence": "equivalent"
                            }
                        ]
                    },
                    {
                        "code": "26999.1",
                        "display": "Other Significant Changes at Margin",
                        "target": [
                            {
                                "code": "",
                                "display": "",
                                "equivalence": "equivalent"
                            }
                        ]
                    },
                    {
                        "code": "27000.1",
                        "display": "Low-grade dysplasia",
                        "target": [
                            {
                                "code": "",
                                "display": "",
                                "equivalence": "equivalent"
                            }
                        ]
                    },
                    {
                        "code": "27605.1",
                        "display": "Specify Margin(s)",
                        "target": [
                            {
                                "code": "",
                                "display": "",
                                "equivalence": "equivalent"
                            }
                        ]
                    },
                    {
                        "code": "27001.1",
                        "display": "Proximal mucosal margin",
                        "target": [
                            {
                                "code": "",
                                "display": "",
                                "equivalence": "equivalent"
                            }
                        ]
                    },
                    {
                        "code": "27002.1",
                        "display": "Distal mucosal margin",
                        "target": [
                            {
                                "code": "",
                                "display": "",
                                "equivalence": "equivalent"
                            }
                        ]
                    },
                    {
                        "code": "27004.1",
                        "display": "Other margin(s) (specify)#",
                        "target": [
                            {
                                "code": "",
                                "display": "",
                                "equivalence": "equivalent"
                            }
                        ]
                    },
                    {
                        "code": "27006.1",
                        "display": "Non-invasive low-grade urothelial carcinoma",
                        "target": [
                            {
                                "code": "",
                                "display": "",
                                "equivalence": "equivalent"
                            }
                        ]
                    },
                    {
                        "code": "27606.1",
                        "display": "Specify Margin(s)",
                        "target": [
                            {
                                "code": "",
                                "display": "",
                                "equivalence": "equivalent"
                            }
                        ]
                    },
                    {
                        "code": "27031.1",
                        "display": "Proximal mucosal margin",
                        "target": [
                            {
                                "code": "",
                                "display": "",
                                "equivalence": "equivalent"
                            }
                        ]
                    },
                    {
                        "code": "27032.1",
                        "display": "Distal mucosal margin",
                        "target": [
                            {
                                "code": "",
                                "display": "",
                                "equivalence": "equivalent"
                            }
                        ]
                    },
                    {
                        "code": "27034.1",
                        "display": "Other margin(s) (specify)#",
                        "target": [
                            {
                                "code": "",
                                "display": "",
                                "equivalence": "equivalent"
                            }
                        ]
                    },
                    {
                        "code": "18102.1",
                        "display": "ACCESSORY FINDINGS",
                        "target": [
                            {
                                "code": "",
                                "display": "",
                                "equivalence": "equivalent"
                            }
                        ]
                    },
                    {
                        "code": "12567.1",
                        "display": "Tumor Configuration",
                        "target": [
                            {
                                "code": "",
                                "display": "",
                                "equivalence": "equivalent"
                            }
                        ]
                    },
                    {
                        "code": "12568.1",
                        "display": "Papillary",
                        "target": [
                            {
                                "code": "",
                                "display": "",
                                "equivalence": "equivalent"
                            }
                        ]
                    },
                    {
                        "code": "12569.1",
                        "display": "Solid / nodule",
                        "target": [
                            {
                                "code": "",
                                "display": "",
                                "equivalence": "equivalent"
                            }
                        ]
                    },
                    {
                        "code": "12570.1",
                        "display": "Ulcerated",
                        "target": [
                            {
                                "code": "",
                                "display": "",
                                "equivalence": "equivalent"
                            }
                        ]
                    },
                    {
                        "code": "12571.1",
                        "display": "Flat",
                        "target": [
                            {
                                "code": "",
                                "display": "",
                                "equivalence": "equivalent"
                            }
                        ]
                    },
                    {
                        "code": "12608.1",
                        "display": "Indeterminate",
                        "target": [
                            {
                                "code": "",
                                "display": "",
                                "equivalence": "equivalent"
                            }
                        ]
                    },
                    {
                        "code": "12611.1",
                        "display": "Other (specify)",
                        "target": [
                            {
                                "code": "",
                                "display": "",
                                "equivalence": "equivalent"
                            }
                        ]
                    },
                    {
                        "code": "12727.1",
                        "display": "Lymph-Vascular Invasion (Note H)",
                        "target": [
                            {
                                "code": "",
                                "display": "",
                                "equivalence": "equivalent"
                            }
                        ]
                    },
                    {
                        "code": "12728.1",
                        "display": "Not identified",
                        "target": [
                            {
                                "code": "47492008 |Not seen (qualifier value)|",
                                "display": "",
                                "equivalence": "equivalent"
                            }
                        ]
                    },
                    {
                        "code": "12729.1",
                        "display": "Present",
                        "target": [
                            {
                                "code": "52101004 |Present (qualifier value)|",
                                "display": "",
                                "equivalence": "equivalent"
                            }
                        ]
                    },
                    {
                        "code": "12730.1",
                        "display": "Indeterminate",
                        "target": [
                            {
                                "code": "",
                                "display": "",
                                "equivalence": "equivalent"
                            }
                        ]
                    },
                    {
                        "code": "18106.1",
                        "display": "STAGE  (pTNM, AJCC 8th ed.)",
                        "target": [
                            {
                                "code": "",
                                "display": "",
                                "equivalence": "equivalent"
                            }
                        ]
                    },
                    {
                        "code": "21076.1",
                        "display": "?TNM Descriptors",
                        "target": [
                            {
                                "code": "",
                                "display": "",
                                "equivalence": "equivalent"
                            }
                        ]
                    },
                    {
                        "code": "8511.100004",
                        "display": "?Not applicable",
                        "target": [
                            {
                                "code": "",
                                "display": "",
                                "equivalence": "equivalent"
                            }
                        ]
                    },
                    {
                        "code": "21078.1",
                        "display": "m (multiple)",
                        "target": [
                            {
                                "code": "",
                                "display": "",
                                "equivalence": "equivalent"
                            }
                        ]
                    },
                    {
                        "code": "21080.1",
                        "display": "r (recurrent)",
                        "target": [
                            {
                                "code": "",
                                "display": "",
                                "equivalence": "equivalent"
                            }
                        ]
                    },
                    {
                        "code": "21081.1",
                        "display": "y (post-treatment)",
                        "target": [
                            {
                                "code": "",
                                "display": "",
                                "equivalence": "equivalent"
                            }
                        ]
                    },
                    {
                        "code": "37953.1",
                        "display": "Primary Tumor (pT)",
                        "target": [
                            {
                                "code": "",
                                "display": "",
                                "equivalence": "equivalent"
                            }
                        ]
                    },
                    {
                        "code": "37954.1",
                        "display": "pTX: Primary tumor cannot be assessed",
                        "target": [
                            {
                                "code": "",
                                "display": "",
                                "equivalence": "equivalent"
                            }
                        ]
                    },
                    {
                        "code": "37955.1",
                        "display": "pT0: No evidence of primary tumor",
                        "target": [
                            {
                                "code": "",
                                "display": "",
                                "equivalence": "equivalent"
                            }
                        ]
                    },
                    {
                        "code": "37956.1",
                        "display": "pTa: Papillary noninvasive carcinoma",
                        "target": [
                            {
                                "code": "",
                                "display": "",
                                "equivalence": "equivalent"
                            }
                        ]
                    },
                    {
                        "code": "37957.1",
                        "display": "pTis: Carcinoma in situ",
                        "target": [
                            {
                                "code": "",
                                "display": "",
                                "equivalence": "equivalent"
                            }
                        ]
                    },
                    {
                        "code": "37958.1",
                        "display": "pT1: Tumor invades subepithelial connective tissue",
                        "target": [
                            {
                                "code": "",
                                "display": "",
                                "equivalence": "equivalent"
                            }
                        ]
                    },
                    {
                        "code": "37959.1",
                        "display": "pT2: Tumor invades the muscularis",
                        "target": [
                            {
                                "code": "",
                                "display": "",
                                "equivalence": "equivalent"
                            }
                        ]
                    },
                    {
                        "code": "37960.1",
                        "display": "pT3: Tumor invades beyond muscularis into periureteric fat",
                        "target": [
                            {
                                "code": "",
                                "display": "",
                                "equivalence": "equivalent"
                            }
                        ]
                    },
                    {
                        "code": "37961.1",
                        "display": "pT4: Tumor invades adjacent organs, or through the kidney into the perinephric fat",
                        "target": [
                            {
                                "code": "",
                                "display": "",
                                "equivalence": "equivalent"
                            }
                        ]
                    },
                    {
                        "code": "37962.1",
                        "display": "Regional Lymph Nodes (pN)",
                        "target": [
                            {
                                "code": "",
                                "display": "",
                                "equivalence": "equivalent"
                            }
                        ]
                    },
                    {
                        "code": "37963.1",
                        "display": "pNX: Regional lymph nodes cannot be assessed",
                        "target": [
                            {
                                "code": "",
                                "display": "",
                                "equivalence": "equivalent"
                            }
                        ]
                    },
                    {
                        "code": "37964.1",
                        "display": "pN0: No regional lymph node metastasis",
                        "target": [
                            {
                                "code": "",
                                "display": "",
                                "equivalence": "equivalent"
                            }
                        ]
                    },
                    {
                        "code": "37965.1",
                        "display": "pN1: Metastasis in a single lymph node, <= 2 cm in greatest dimension",
                        "target": [
                            {
                                "code": "",
                                "display": "",
                                "equivalence": "equivalent"
                            }
                        ]
                    },
                    {
                        "code": "37966.1",
                        "display": "pN2: Metastasis in a single lymph node, > 2 cm; or multiple lymph nodes",
                        "target": [
                            {
                                "code": "",
                                "display": "",
                                "equivalence": "equivalent"
                            }
                        ]
                    },
                    {
                        "code": "11816.1",
                        "display": "",
                        "target": [
                            {
                                "code": "",
                                "display": "",
                                "equivalence": "equivalent"
                            }
                        ]
                    },
                    {
                        "code": "11817.1",
                        "display": "No nodes submitted or found",
                        "target": [
                            {
                                "code": "",
                                "display": "",
                                "equivalence": "equivalent"
                            }
                        ]
                    },
                    {
                        "code": "11823.1",
                        "display": "Number of Lymph Nodes Examined",
                        "target": [
                            {
                                "code": "",
                                "display": "",
                                "equivalence": "equivalent"
                            }
                        ]
                    },
                    {
                        "code": "11824.1",
                        "display": "Specify",
                        "target": [
                            {
                                "code": "",
                                "display": "",
                                "equivalence": "equivalent"
                            }
                        ]
                    },
                    {
                        "code": "11825.1",
                        "display": "Number cannot be determined (explain)",
                        "target": [
                            {
                                "code": "",
                                "display": "",
                                "equivalence": "equivalent"
                            }
                        ]
                    },
                    {
                        "code": "11826.1",
                        "display": "Number of Lymph Nodes Involved (any size)",
                        "target": [
                            {
                                "code": "",
                                "display": "",
                                "equivalence": "equivalent"
                            }
                        ]
                    },
                    {
                        "code": "11827.1",
                        "display": "Specify",
                        "target": [
                            {
                                "code": "",
                                "display": "",
                                "equivalence": "equivalent"
                            }
                        ]
                    },
                    {
                        "code": "11828.1",
                        "display": "Number cannot be determined (explain)",
                        "target": [
                            {
                                "code": "",
                                "display": "",
                                "equivalence": "equivalent"
                            }
                        ]
                    },
                    {
                        "code": "12563.1",
                        "display": "?Distant Metastasis (pM)",
                        "target": [
                            {
                                "code": "",
                                "display": "",
                                "equivalence": "equivalent"
                            }
                        ]
                    },
                    {
                        "code": "21077.1",
                        "display": "?Not applicable - pM cannot be determined from the submitted specimen(s)",
                        "target": [
                            {
                                "code": "",
                                "display": "",
                                "equivalence": "equivalent"
                            }
                        ]
                    },
                    {
                        "code": "12565.1",
                        "display": "pM1: Distant metastasis",
                        "target": [
                            {
                                "code": "",
                                "display": "",
                                "equivalence": "equivalent"
                            }
                        ]
                    },
                    {
                        "code": "12566.1",
                        "display": "?Specify Site(s), if known",
                        "target": [
                            {
                                "code": "",
                                "display": "",
                                "equivalence": "equivalent"
                            }
                        ]
                    },
                    {
                        "code": "18107.1",
                        "display": "ADDITIONAL NON-TUMOR",
                        "target": [
                            {
                                "code": "",
                                "display": "",
                                "equivalence": "equivalent"
                            }
                        ]
                    },
                    {
                        "code": "12259.1",
                        "display": "Associated Epithelial Lesions (Note C)",
                        "target": [
                            {
                                "code": "",
                                "display": "",
                                "equivalence": "equivalent"
                            }
                        ]
                    },
                    {
                        "code": "12260.1",
                        "display": "None identified",
                        "target": [
                            {
                                "code": "",
                                "display": "",
                                "equivalence": "equivalent"
                            }
                        ]
                    },
                    {
                        "code": "12261.1",
                        "display": "Urothelial (transitional cell) papilloma (World Health Organization [WHO] / International Society of Urologic Pathology [ISUP], 1998; WHO 2004)",
                        "target": [
                            {
                                "code": "",
                                "display": "",
                                "equivalence": "equivalent"
                            }
                        ]
                    },
                    {
                        "code": "12262.1",
                        "display": "Urothelial (transitional cell) papilloma, inverted type",
                        "target": [
                            {
                                "code": "",
                                "display": "",
                                "equivalence": "equivalent"
                            }
                        ]
                    },
                    {
                        "code": "12263.1",
                        "display": "Papillary urothelial (transitional cell) neoplasm, low malignant potential (WHO / ISUP 1998; WHO 2004)",
                        "target": [
                            {
                                "code": "",
                                "display": "",
                                "equivalence": "equivalent"
                            }
                        ]
                    },
                    {
                        "code": "12264.1",
                        "display": "Cannot be determined",
                        "target": [
                            {
                                "code": "1156316003 |Cannot be determined (qualifier value)|",
                                "display": "",
                                "equivalence": "equivalent"
                            }
                        ]
                    },
                    {
                        "code": "12731.1",
                        "display": "Additional Pathologic Findings",
                        "target": [
                            {
                                "code": "",
                                "display": "",
                                "equivalence": "equivalent"
                            }
                        ]
                    },
                    {
                        "code": "12733.1",
                        "display": "Urothelial dysplasia (low-grade intraurothelial neoplasia)",
                        "target": [
                            {
                                "code": "",
                                "display": "",
                                "equivalence": "equivalent"
                            }
                        ]
                    },
                    {
                        "code": "12734.1",
                        "display": "Inflammation / regenerative changes",
                        "target": [
                            {
                                "code": "",
                                "display": "",
                                "equivalence": "equivalent"
                            }
                        ]
                    },
                    {
                        "code": "12735.1",
                        "display": "Therapy-related changes",
                        "target": [
                            {
                                "code": "",
                                "display": "",
                                "equivalence": "equivalent"
                            }
                        ]
                    },
                    {
                        "code": "12760.1",
                        "display": "Ureteritis cystica et glandularis",
                        "target": [
                            {
                                "code": "",
                                "display": "",
                                "equivalence": "equivalent"
                            }
                        ]
                    },
                    {
                        "code": "12764.1",
                        "display": "Keratinizing squamous metaplasia",
                        "target": [
                            {
                                "code": "",
                                "display": "",
                                "equivalence": "equivalent"
                            }
                        ]
                    },
                    {
                        "code": "12768.1",
                        "display": "Intestinal metaplasia",
                        "target": [
                            {
                                "code": "",
                                "display": "",
                                "equivalence": "equivalent"
                            }
                        ]
                    },
                    {
                        "code": "12819.1",
                        "display": "Other (specify)",
                        "target": [
                            {
                                "code": "",
                                "display": "",
                                "equivalence": "equivalent"
                            }
                        ]
                    },
                    {
                        "code": "12820.1",
                        "display": "Comment(s)",
                        "target": [
                            {
                                "code": "",
                                "display": "",
                                "equivalence": "equivalent"
                            }
                        ]
                    },
                    {
                        "code": "12441.1",
                        "display": "Primary Tumor (pT)",
                        "target": [
                            {
                                "code": "",
                                "display": "",
                                "equivalence": "equivalent"
                            }
                        ]
                    },
                    {
                        "code": "12444.1",
                        "display": "pTX: Cannot be assessed",
                        "target": [
                            {
                                "code": "",
                                "display": "",
                                "equivalence": "equivalent"
                            }
                        ]
                    },
                    {
                        "code": "12445.1",
                        "display": "pT0: No evidence of primary tumor",
                        "target": [
                            {
                                "code": "",
                                "display": "",
                                "equivalence": "equivalent"
                            }
                        ]
                    },
                    {
                        "code": "12460.1",
                        "display": "pTa: Papillary noninvasive carcinoma",
                        "target": [
                            {
                                "code": "",
                                "display": "",
                                "equivalence": "equivalent"
                            }
                        ]
                    },
                    {
                        "code": "12477.1",
                        "display": "pTis: Carcinoma in situ",
                        "target": [
                            {
                                "code": "",
                                "display": "",
                                "equivalence": "equivalent"
                            }
                        ]
                    },
                    {
                        "code": "12486.1",
                        "display": "pT1: Tumor invades subepithelial connective tissue (lamina propria)",
                        "target": [
                            {
                                "code": "",
                                "display": "",
                                "equivalence": "equivalent"
                            }
                        ]
                    },
                    {
                        "code": "12508.1",
                        "display": "pT2: Tumor invades the muscularis propria",
                        "target": [
                            {
                                "code": "",
                                "display": "",
                                "equivalence": "equivalent"
                            }
                        ]
                    },
                    {
                        "code": "12509.1",
                        "display": "pT3: Tumor invades beyond muscularis propria into periureteric fat",
                        "target": [
                            {
                                "code": "",
                                "display": "",
                                "equivalence": "equivalent"
                            }
                        ]
                    },
                    {
                        "code": "12535.1",
                        "display": "pT4: Tumor invades adjacent organs",
                        "target": [
                            {
                                "code": "",
                                "display": "",
                                "equivalence": "equivalent"
                            }
                        ]
                    },
                    {
                        "code": "12538.1",
                        "display": "Regional Lymph Nodes (pN)",
                        "target": [
                            {
                                "code": "",
                                "display": "",
                                "equivalence": "equivalent"
                            }
                        ]
                    },
                    {
                        "code": "12539.1",
                        "display": "pNX: Cannot be assessed",
                        "target": [
                            {
                                "code": "",
                                "display": "",
                                "equivalence": "equivalent"
                            }
                        ]
                    },
                    {
                        "code": "12540.1",
                        "display": "pN0: No regional lymph node metastasis",
                        "target": [
                            {
                                "code": "",
                                "display": "",
                                "equivalence": "equivalent"
                            }
                        ]
                    },
                    {
                        "code": "12558.1",
                        "display": "pN1: Metastasis in a single regional lymph node, 2 cm or less in greatest dimension",
                        "target": [
                            {
                                "code": "",
                                "display": "",
                                "equivalence": "equivalent"
                            }
                        ]
                    },
                    {
                        "code": "12559.1",
                        "display": "pN2: Metastasis in a single regional lymph node, more than 2 cm but not more than 5 cm in greatest dimension, or multiple lymph nodes, none more than 5 cm in greatest dimension",
                        "target": [
                            {
                                "code": "",
                                "display": "",
                                "equivalence": "equivalent"
                            }
                        ]
                    },
                    {
                        "code": "12560.1",
                        "display": "pN3: Metastasis in a regional lymph node more than 5 cm in greatest dimension",
                        "target": [
                            {
                                "code": "",
                                "display": "",
                                "equivalence": "equivalent"
                            }
                        ]
                    },
                    {
                        "code": "26659.1",
                        "display": "Histologic Grade (Note C) (select appropriate histologic category and grade)",
                        "target": [
                            {
                                "code": "",
                                "display": "",
                                "equivalence": "equivalent"
                            }
                        ]
                    },
                    {
                        "code": "26656.1",
                        "display": "Urothelial carcinoma",
                        "target": [
                            {
                                "code": "",
                                "display": "",
                                "equivalence": "equivalent"
                            }
                        ]
                    },
                    {
                        "code": "12274.1",
                        "display": "",
                        "target": [
                            {
                                "code": "",
                                "display": "",
                                "equivalence": "equivalent"
                            }
                        ]
                    },
                    {
                        "code": "26657.1",
                        "display": "Squamous cell carcinoma and adenocarcinoma",
                        "target": [
                            {
                                "code": "",
                                "display": "",
                                "equivalence": "equivalent"
                            }
                        ]
                    },
                    {
                        "code": "12432.1",
                        "display": "",
                        "target": [
                            {
                                "code": "",
                                "display": "",
                                "equivalence": "equivalent"
                            }
                        ]
                    },
                    {
                        "code": "12439.1",
                        "display": "Other (specify)",
                        "target": [
                            {
                                "code": "",
                                "display": "",
                                "equivalence": "equivalent"
                            }
                        ]
                    },
                    {
                        "code": "26658.1",
                        "display": "Other carcinoma",
                        "target": [
                            {
                                "code": "",
                                "display": "",
                                "equivalence": "equivalent"
                            }
                        ]
                    },
                    {
                        "code": "26607.1",
                        "display": "",
                        "target": [
                            {
                                "code": "",
                                "display": "",
                                "equivalence": "equivalent"
                            }
                        ]
                    },
                    {
                        "code": "26609.1",
                        "display": "Low-grade",
                        "target": [
                            {
                                "code": "",
                                "display": "",
                                "equivalence": "equivalent"
                            }
                        ]
                    },
                    {
                        "code": "26610.1",
                        "display": "High-grade",
                        "target": [
                            {
                                "code": "",
                                "display": "",
                                "equivalence": "equivalent"
                            }
                        ]
                    },
                    {
                        "code": "26611.1",
                        "display": "Other (specify)",
                        "target": [
                            {
                                "code": "",
                                "display": "",
                                "equivalence": "equivalent"
                            }
                        ]
                    }
                ]
            }
        ]
    }
]